tabler_icons/__init__.py
tabler_icons/archive.zip
tabler_icons/icons.py
tabler_icons/templatetags/__init__.py
tabler_icons/templatetags/tabler_icons.py
tabler_icons-0.5.0.dist-info/LICENSE
tabler_icons-0.5.0.dist-info/METADATA
tabler_icons-0.5.0.dist-info/WHEEL
tabler_icons-0.5.0.dist-info/RECORD
