Metadata-Version: 2.1
Name: tabler-icons
Version: 0.5.0
Summary: SVG tabler icons for your apps.
Home-page: https://github.com/alex-oleshkevich/tabler_icons
License: MIT
Author: Alex Oleshkevich
Author-email: alex.oleshkevich@gmail.com
Requires-Python: >=3.9.0,<4.0.0
Classifier: Development Status :: 5 - Production/Stable
Classifier: Environment :: Web Environment
Classifier: Intended Audience :: Developers
Classifier: License :: OSI Approved :: MIT License
Classifier: Operating System :: OS Independent
Classifier: Programming Language :: Python :: 3
Classifier: Programming Language :: Python :: 3.9
Classifier: Programming Language :: Python :: 3.10
Classifier: Programming Language :: Python :: 3.11
Classifier: Programming Language :: Python :: 3
Classifier: Programming Language :: Python :: 3.10
Classifier: Programming Language :: Python :: 3.9
Classifier: Topic :: Software Development :: Libraries :: Python Modules
Classifier: Typing :: Typed
Requires-Dist: markupsafe
Project-URL: Documentation, https://github.com/alex-oleshkevich/tabler_icons
Project-URL: Repository, https://github.com/alex-oleshkevich/tabler_icons
